instagram_profile/__init__.py
instagram_profile/admin.py
instagram_profile/apps.py
instagram_profile/client.py
instagram_profile/models.py
instagram_profile/profiles.py
instagram_profile/services.py
instagram_profile/settings.py
instagram_profile/tests.py
instagram_profile/urls.py
instagram_profile/views.py
instagram_profile/management/__init__.py
instagram_profile/management/commands/__init__.py
instagram_profile/management/commands/sync_instagram_posts.py
instagram_profile/migrations/0001_initial.py
instagram_profile/migrations/0002_auto_20200629_1325.py
instagram_profile/migrations/__init__.py
instagram_profile/templates/admin/instagram_profile/change_list_object_tools.html
instagram_profile/templates/admin/instagram_profile/post/change_list.html
instagram_profile/templates/admin/instagram_profile/profile/change_form.html
instagram_profile/templates/instagram_profile/feed.html
django_instagram_profile-1.0.3.dist-info/LICENSE
django_instagram_profile-1.0.3.dist-info/METADATA
django_instagram_profile-1.0.3.dist-info/WHEEL
django_instagram_profile-1.0.3.dist-info/top_level.txt
django_instagram_profile-1.0.3.dist-info/RECORD
